inventory_explorer/__init__.py
inventory_explorer/aliases.py
inventory_explorer/ansible.py
inventory_explorer/app.py
inventory_explorer/background_processing.py
inventory_explorer/py.typed
inventory_explorer/tui.py
inventory_explorer-0.0.1.dist-info/licenses/LICENSE
inventory_explorer-0.0.1.dist-info/METADATA
inventory_explorer-0.0.1.dist-info/WHEEL
inventory_explorer-0.0.1.dist-info/entry_points.txt
inventory_explorer-0.0.1.dist-info/top_level.txt
inventory_explorer-0.0.1.dist-info/RECORD
