Metadata-Version: 2.4
Name: inventory-explorer
Version: 0.0.1
Summary: A tool for efficiently exploring the hosts, groups and variables in an Ansible inventory
License:                                  Apache License
License-File: LICENSE
Requires-Dist: pyyaml
Requires-Dist: fzy
Dynamic: license-file
